dj_docs/__init__.py
dj_docs/apps.py
dj_docs/notepads.py
dj_docs/urls.py
dj_docs/utils.py
dj_docs/views.py
dj_docs/management/__init__.py
dj_docs/management/commands/__init__.py
dj_docs/management/commands/create_docs.py
dj_docs/management/commands/update_docs.py
dj_docs/management/commands/hints/__init__.py
dj_docs/management/commands/hints/configuration.md
dj_docs/management/commands/hints/intro.md
dj_docs/migrations/__init__.py
dj_docs-0.1.dist-info/LICENSE
dj_docs-0.1.dist-info/METADATA
dj_docs-0.1.dist-info/WHEEL
dj_docs-0.1.dist-info/top_level.txt
dj_docs-0.1.dist-info/RECORD
