Metadata-Version: 2.1
Name: dj-docs
Version: 0.1
Summary: django application for documentation
Author: Sreeshanth
Author-email: sreeshanththekkedath8@gmail.com
Maintainer: Sreeshanth
Maintainer-email: sreeshanththekkedath8@gmail.com
License: MIT
Keywords: django docs,docs
Classifier: Environment :: Web Environment
Classifier: Framework :: Django
Classifier: Intended Audience :: Developers
Classifier: License :: OSI Approved :: MIT License
Classifier: Operating System :: OS Independent
Classifier: Programming Language :: Python :: 3
Classifier: Programming Language :: Python :: 3.5
Classifier: Programming Language :: Python :: 3.6
Classifier: Programming Language :: Python :: 3.7
Classifier: Programming Language :: Python :: 3.8
Classifier: Programming Language :: Python :: 3.9
Classifier: Programming Language :: Python :: 3.10
Classifier: Topic :: Software Development :: Libraries :: Python Modules
License-File: LICENSE
Requires-Dist: django (>=3)
Requires-Dist: pygments (==2.14.0)
Requires-Dist: myst-parser (==1.0.0)
Requires-Dist: sphinx (==6.1.3)
Requires-Dist: sphinx-rtd-theme (==1.2.0)
